{
  "$schema": "https://raw.githubusercontent.com/DjobaDELATV/seygo_data/main/schema/v1/card.json",
  "id": "bf586d0e-ae86-4c2c-8321-73c7a35563a2",
  "text": {
    "en": {
      "name": "Dark Magic Veil",
      "effect": "Pay 1000 LP; Special Summon 1 DARK Spellcaster-Type monster from your hand or Graveyard."
    },
    "fr": {
      "name": "Voile de Magie Noire",
      "effect": "Payez 1000 LP ; Invoquez Sp\u00e9cialement 1 monstre T\u00c9N\u00c8BRES de Type Magicien depuis votre main ou Cimeti\u00e8re."
    },
    "de": {
      "name": "Dunkler magischer Schleier",
      "effect": "Zahle 1000 LP; beschw\u00f6re 1 FINSTERNIS Monster vom Typ Hexer als Spezialbeschw\u00f6rung von deiner Hand oder deinem Friedhof."
    },
    "it": {
      "name": "Velo Magico Nero",
      "effect": "Paga 1000 LP; Evoca Specialmente 1 mostro OSCURIT\u00c0 di Tipo Incantatore dalla tua mano o Cimitero."
    },
    "pt": {
      "name": "V\u00e9u do Mago Negro",
      "effect": "Pague 1000 PV; Invoque por Invoca\u00e7\u00e3o-Especial 1 monstro de TREVAS do Tipo Mago da sua m\u00e3o ou Cemit\u00e9rio."
    },
    "es": {
      "name": "Velo de Magia Oscura",
      "effect": "Paga 1000 LP; Invoca de Modo Especial, desde tu mano o Cementerio, 1 monstruo de Tipo Lanzador de Conjuros de OSCURIDAD."
    },
    "ja": {
      "name": "\u9ed2\u9b54\u8853\u306e\u30f4\u30a7\u30fc\u30eb",
      "effect": "\u2460\uff1a\uff11\uff10\uff10\uff10\uff2c\uff30\u3092\u6255\u3063\u3066\u767a\u52d5\u3067\u304d\u308b\u3002\u81ea\u5206\u306e\u624b\u672d\u30fb\u5893\u5730\u304b\u3089\u9b54\u6cd5\u4f7f\u3044\u65cf\u30fb\u95c7\u5c5e\u6027\u30e2\u30f3\u30b9\u30bf\u30fc\uff11\u4f53\u3092\u9078\u3093\u3067\u7279\u6b8a\u53ec\u559a\u3059\u308b\u3002"
    },
    "ko": {
      "name": "\ud751\ub9c8\uc220\uc758 \ubca0\uc77c",
      "effect": "\u2460: 1000 LP\ub97c \uc9c0\ubd88\ud558\uace0 \ubc1c\ub3d9\ud560 \uc218 \uc788\ub2e4. \uc790\uc2e0\uc758 \ud328 / \ubb18\uc9c0\uc5d0\uc11c \ub9c8\ubc95\uc0ac\uc871 / \uc5b4\ub460 \uc18d\uc131 \ubaac\uc2a4\ud130 1\uc7a5\uc744 \uace0\ub974\uace0 \ud2b9\uc218 \uc18c\ud658\ud55c\ub2e4."
    }
  },
  "cardType": "spell",
  "subcategory": "normal",
  "passwords": [
    "82404868"
  ],
  "images": [
    {
      "id": "2560f3c2-4ab0-4e3a-b837-c65fed25377b",
      "password": "82404868",
      "art": "https://images.ygoprodeck.com/images/cards_cropped/82404868.jpg",
      "card": "https://images.ygoprodeck.com/images/cards/82404868.jpg",
      "lastChecked": "2026-06-14T08:10:08.619770"
    }
  ],
  "sets": [
    "e3d9812a-7bd0-4825-9968-69038ad4488a",
    "e3d9812a-7bd0-4825-9968-69038ad4488a",
    "e3d9812a-7bd0-4825-9968-69038ad4488a",
    "e3d9812a-7bd0-4825-9968-69038ad4488a",
    "e3d9812a-7bd0-4825-9968-69038ad4488a",
    "e3d9812a-7bd0-4825-9968-69038ad4488a",
    "e3d9812a-7bd0-4825-9968-69038ad4488a",
    "e3d9812a-7bd0-4825-9968-69038ad4488a",
    "a75200ca-2140-4bb4-8ab9-ec8d51d7b007",
    "a75200ca-2140-4bb4-8ab9-ec8d51d7b007",
    "a75200ca-2140-4bb4-8ab9-ec8d51d7b007",
    "a75200ca-2140-4bb4-8ab9-ec8d51d7b007",
    "a75200ca-2140-4bb4-8ab9-ec8d51d7b007",
    "a75200ca-2140-4bb4-8ab9-ec8d51d7b007",
    "71391ee2-f94e-4d47-8f2e-febfd50b9ec3",
    "71391ee2-f94e-4d47-8f2e-febfd50b9ec3",
    "71391ee2-f94e-4d47-8f2e-febfd50b9ec3",
    "71391ee2-f94e-4d47-8f2e-febfd50b9ec3",
    "71391ee2-f94e-4d47-8f2e-febfd50b9ec3",
    "71391ee2-f94e-4d47-8f2e-febfd50b9ec3",
    "74756588-a6ab-4ffb-b2fc-6c9e74605583",
    "74756588-a6ab-4ffb-b2fc-6c9e74605583",
    "74756588-a6ab-4ffb-b2fc-6c9e74605583",
    "74756588-a6ab-4ffb-b2fc-6c9e74605583",
    "34d3bf2d-0339-47b7-a378-0baea64b2717",
    "801bb331-1937-4f23-88cf-d03e0a497f92",
    "e4496caa-2cad-4db2-8efb-34ae80607903",
    "e5a1a65a-3652-4b88-a62b-0e794b136d7b",
    "0fdaf5e2-ec63-4ea6-809e-4f181a1017a9"
  ],
  "legality": {
    "tcg": {
      "current": "unlimited",
      "currentLegality": "unlimited"
    },
    "ocg": {
      "current": "unlimited",
      "currentLegality": "unlimited"
    },
    "genesys": {
      "current": "unlimited",
      "currentLegality": "unlimited",
      "currentPoints": 0
    }
  },
  "masterDuel": {
    "rarity": "r",
    "craftable": true
  },
  "duelLinks": {
    "rarity": "r"
  },
  "externalIDs": {
    "yugipedia": [
      {
        "name": "Dark Magic Veil",
        "id": 445976
      }
    ],
    "dbID": 12502,
    "ygoprodeck": {
      "id": 82404868,
      "name": "dark-magic-veil-6928"
    },
    "yamlyugiID": 82404868
  },
  "series": []
}