{
  "$schema": "https://raw.githubusercontent.com/DjobaDELATV/seygo_data/main/schema/v1/card.json",
  "id": "d14bab8f-5422-4049-81f0-cb1e36699a4a",
  "text": {
    "en": {
      "name": "Spell Counter (card)",
      "effect": "This card can be used as a \"Spell Counter\".",
      "official": false
    },
    "fr": {
      "name": "Compteur Magie"
    },
    "de": {
      "name": "Zauberz\u00e4hlmarke"
    },
    "it": {
      "name": "Segnalino Magia"
    },
    "pt": {
      "name": "Marcador de Magia"
    },
    "es": {
      "name": "Contador M\u00e1gico"
    },
    "ja": {
      "name": "\u9b54\u529b\u30ab\u30a6\u30f3\u30bf\u30fc",
      "effect": "\u3053\u306e\u30ab\u30fc\u30c9\u306f\u300e\u9b54\u529b\u30ab\u30a6\u30f3\u30bf\u30fc\u300f\u3068\u3057\u3066\u4f7f\u7528\u3059\u308b\u4e8b\u304c\u3067\u304d\u308b\u3002"
    },
    "ko": {
      "name": "\ub9c8\ub825 \uce74\uc6b4\ud130",
      "effect": "\uc774 \uce74\ub4dc\ub294 \u300c\ub9c8\ub825 \uce74\uc6b4\ud130\u300d\ub85c \uc0ac\uc6a9\ud560 \uc218 \uc788\ub2e4."
    },
    "zh-CN": {
      "name": "\u9b54\u529b\u8ba1\u6570\u7269"
    }
  },
  "cardType": "token",
  "passwords": [],
  "images": [
    {
      "id": "0ce0eeaf-48fa-406e-90ad-82052345e31e",
      "card": "https://ms.yugipedia.com//a/a3/SpellCounter-19TP-JP-C.png",
      "lastChecked": "2026-06-14T08:30:40.328367"
    }
  ],
  "sets": [
    "2da9381f-31af-47d2-b142-79241d5c1924",
    "b3c8cf92-19f4-4c42-8b83-8c5c169506a2",
    "f945159b-cba7-4f17-a5b5-e83564f19fce",
    "160afc42-8b73-4987-aae6-8bc297492951"
  ],
  "legality": {},
  "externalIDs": {
    "yugipedia": [
      {
        "name": "Spell Counter (card)",
        "id": 354093
      }
    ]
  },
  "series": []
}