{
  "$schema": "https://raw.githubusercontent.com/iconmaster5326/YGOJSON/main/schema/v1/skill.json",
  "id": "4ee4c1e9-e268-45ea-b23e-519f4b60353d",
  "text": {
    "en": {
      "name": "Neo Sylvio",
      "effect": "Can be used once per Duel if you control a monster that was Tribute Summoned. Change 1 Spell/Trap Card in your hand to a different card.\n\u25cf Spell Card: Frost Blast of the Monarchs\n\u25cf Trap Card: The Monarchs Awaken"
    },
    "fr": {
      "name": "N\u00e9o Sylvio",
      "effect": "Cette Comp\u00e9tence peut \u00eatre utilis\u00e9e une fois par Duel si vous contr\u00f4lez un monstre qui a \u00e9t\u00e9 Invoqu\u00e9 par Sacrifice. Remplacez 1 Carte Magie/Pi\u00e8ge de votre main par une autre carte.\n* Carte Magie : Souffle de Gel\u00e9e des Monarques\n* Carte Pi\u00e8ge : Le R\u00e9veil des Monarques"
    },
    "ja": {
      "name": ""
    }
  },
  "cardType": "skill-dl",
  "skillType": "Legendary",
  "supports": [
    "Frost Blast of the Monarchs (Duel Links)",
    "The Monarchs Awaken (Duel Links)"
  ],
  "releases": [
    {
      "character": "Sylvio Sawatari (Duel Links)",
      "type": "level_up"
    }
  ],
  "externalIDs": {
    "yugipedia": [
      {
        "name": "Neo Sylvio",
        "id": 716023
      }
    ]
  }
}