{
  "$schema": "https://raw.githubusercontent.com/iconmaster5326/YGOJSON/main/schema/v1/skill.json",
  "id": "788941e1-cfd1-44d8-9279-880deb5bcadd",
  "text": {
    "en": {
      "name": "You'll Pay for This!",
      "effect": "Select 1 monster your opponent controls. Then, the following effect will be applied during the beginning of your next turn. The ATK/DEF of that monster will become half its original ATK/DEF until the end of the turn.This Skill can only be used once per Duel."
    },
    "fr": {
      "name": "Tu vas me le payer !",
      "effect": "S\u00e9lectionnez un monstre que votre adversaire contr\u00f4le. Puis, l'effet suivant sera appliqu\u00e9 pendant le d\u00e9but de votre prochain tour. L'ATK/DEF de ce monstre deviendra la moiti\u00e9 de son ATK/DEF d'origine jusqu'\u00e0 la fin du tour.Cette Comp\u00e9tence ne peut \u00eatre utilis\u00e9e qu'une fois par Duel."
    },
    "ja": {
      "name": ""
    }
  },
  "cardType": "skill-dl",
  "skillType": "Legendary",
  "releases": [
    {
      "character": "Rio Kastle (Duel Links)",
      "type": "duel_reward"
    }
  ],
  "externalIDs": {
    "yugipedia": [
      {
        "name": "You'll Pay for This!",
        "id": 717557
      }
    ]
  }
}