{
  "$schema": "https://raw.githubusercontent.com/iconmaster5326/YGOJSON/main/schema/v1/skill.json",
  "id": "c6c53375-d0f2-4f82-be13-df6ea82403ad",
  "text": {
    "en": {
      "name": "Luck on Your Side",
      "effect": "If your Life Points drop below 1000,\nyour coin tosses always land on heads."
    },
    "fr": {
      "name": "Porte-bohneur",
      "effect": "S'active si vos Life Points tombent en dessous de 1 000.\nVos pi\u00e8ces tombent toujours sur face."
    },
    "ja": {
      "name": "\u904b\u3092\u5473\u65b9\u306b\uff01",
      "effect": "\u81ea\u5206\u306e\u30e9\u30a4\u30d5\u30dd\u30a4\u30f3\u30c8\u304c\uff19\uff19\uff19\u4ee5\u4e0b\u306e\u5834\u5408\u3001\u81ea\u5206\u306e\u30b3\u30a4\u30f3\u30c8\u30b9\u306f\u5fc5\u305a\u8868\u304c\u51fa\u308b\u3002"
    }
  },
  "cardType": "skill-dl",
  "skillType": "Legendary",
  "releases": [
    {
      "character": "Joey Wheeler (Duel Links)",
      "type": "duel_reward"
    }
  ],
  "externalIDs": {
    "yugipedia": [
      {
        "name": "Luck on Your Side",
        "id": 715658
      }
    ]
  }
}