{
  "$schema": "https://raw.githubusercontent.com/DjobaDELATV/seygo_data/main/schema/v1/set.json",
  "id": "09714bc5-c39a-402d-95d1-f4bc03863f02",
  "name": {
    "en": "Duelist League Series 5 participation card",
    "it": "Serie Duelist League 5 carta di partecipazione"
  },
  "locales": {
    "en": {
      "language": "en",
      "prefix": "DL5-EN",
      "date": "2004-01-01",
      "image": "https://ms.yugipedia.com//4/40/DL-PromoEN.jpg",
      "cardImages": {
        "unlimited": {
          "c24e2731-b52a-4602-a6a1-3188b2f4878d": "https://ms.yugipedia.com//1/1a/RestructerRevolution-DL5-EN-SR-UE.png"
        }
      },
      "cardInfo": {
        "unlimited": {
          "c24e2731-b52a-4602-a6a1-3188b2f4878d": {
            "image": "https://ms.yugipedia.com//1/1a/RestructerRevolution-DL5-EN-SR-UE.png"
          }
        }
      },
      "formats": [
        "tcg"
      ],
      "editions": [
        "unlimited"
      ],
      "externalIDs": {
        "dbIDs": [
          1121203001
        ]
      }
    },
    "fr": {
      "language": "fr",
      "prefix": "DL5-FR",
      "date": "2004-09-01",
      "cardImages": {
        "unlimited": {
          "c24e2731-b52a-4602-a6a1-3188b2f4878d": "https://ms.yugipedia.com//d/df/RestructerRevolution-DL5-FR-SR-UE.jpg"
        }
      },
      "cardInfo": {
        "unlimited": {
          "c24e2731-b52a-4602-a6a1-3188b2f4878d": {
            "image": "https://ms.yugipedia.com//d/df/RestructerRevolution-DL5-FR-SR-UE.jpg"
          }
        }
      },
      "formats": [
        "tcg"
      ],
      "editions": [
        "unlimited"
      ],
      "externalIDs": {}
    },
    "de": {
      "language": "de",
      "prefix": "DL5-DE",
      "date": "2004-09-01",
      "cardImages": {
        "unlimited": {
          "c24e2731-b52a-4602-a6a1-3188b2f4878d": "https://ms.yugipedia.com//5/5c/RestructerRevolution-DL5-DE-SR-UE.jpg"
        }
      },
      "cardInfo": {
        "unlimited": {
          "c24e2731-b52a-4602-a6a1-3188b2f4878d": {
            "image": "https://ms.yugipedia.com//5/5c/RestructerRevolution-DL5-DE-SR-UE.jpg"
          }
        }
      },
      "formats": [
        "tcg"
      ],
      "editions": [
        "unlimited"
      ],
      "externalIDs": {}
    },
    "sp": {
      "language": "es",
      "prefix": "DL5-SP",
      "date": "2004-09-01",
      "cardImages": {
        "unlimited": {
          "c24e2731-b52a-4602-a6a1-3188b2f4878d": "https://ms.yugipedia.com//1/16/RestructerRevolution-DL5-SP-SR-UE.png"
        }
      },
      "cardInfo": {
        "unlimited": {
          "c24e2731-b52a-4602-a6a1-3188b2f4878d": {
            "image": "https://ms.yugipedia.com//1/16/RestructerRevolution-DL5-SP-SR-UE.png"
          }
        }
      },
      "formats": [
        "tcg"
      ],
      "editions": [
        "unlimited"
      ],
      "externalIDs": {}
    },
    "it": {
      "language": "it",
      "prefix": "DL5-IT",
      "date": "2004-09-01",
      "cardImages": {
        "unlimited": {
          "c24e2731-b52a-4602-a6a1-3188b2f4878d": "https://ms.yugipedia.com//f/fd/RestructerRevolution-DL5-IT-SR-UE.png"
        }
      },
      "cardInfo": {
        "unlimited": {
          "c24e2731-b52a-4602-a6a1-3188b2f4878d": {
            "image": "https://ms.yugipedia.com//f/fd/RestructerRevolution-DL5-IT-SR-UE.png"
          }
        }
      },
      "formats": [
        "tcg"
      ],
      "editions": [
        "unlimited"
      ],
      "externalIDs": {}
    }
  },
  "contents": [
    {
      "locales": [
        "en"
      ],
      "formats": [
        "tcg"
      ],
      "distrobution": "preconstructed",
      "editions": [
        "unlimited"
      ],
      "image": "https://ms.yugipedia.com//4/40/DL-PromoEN.jpg",
      "cards": [
        {
          "id": "c24e2731-b52a-4602-a6a1-3188b2f4878d",
          "card": "7a02b32e-920d-4448-96f0-4d0a0c02b975",
          "suffix": "001",
          "rarity": "super"
        }
      ],
      "externalIDs": {}
    },
    {
      "locales": [
        "fr"
      ],
      "formats": [
        "tcg"
      ],
      "distrobution": "preconstructed",
      "editions": [
        "unlimited"
      ],
      "cards": [
        {
          "id": "c24e2731-b52a-4602-a6a1-3188b2f4878d",
          "card": "7a02b32e-920d-4448-96f0-4d0a0c02b975",
          "suffix": "001",
          "rarity": "super"
        }
      ],
      "externalIDs": {}
    },
    {
      "locales": [
        "de"
      ],
      "formats": [
        "tcg"
      ],
      "distrobution": "preconstructed",
      "editions": [
        "unlimited"
      ],
      "cards": [
        {
          "id": "c24e2731-b52a-4602-a6a1-3188b2f4878d",
          "card": "7a02b32e-920d-4448-96f0-4d0a0c02b975",
          "suffix": "001",
          "rarity": "super"
        }
      ],
      "externalIDs": {}
    },
    {
      "locales": [
        "sp"
      ],
      "formats": [
        "tcg"
      ],
      "distrobution": "preconstructed",
      "editions": [
        "unlimited"
      ],
      "cards": [
        {
          "id": "c24e2731-b52a-4602-a6a1-3188b2f4878d",
          "card": "7a02b32e-920d-4448-96f0-4d0a0c02b975",
          "suffix": "001",
          "rarity": "super"
        }
      ],
      "externalIDs": {}
    },
    {
      "locales": [
        "it"
      ],
      "formats": [
        "tcg"
      ],
      "distrobution": "preconstructed",
      "editions": [
        "unlimited"
      ],
      "cards": [
        {
          "id": "c24e2731-b52a-4602-a6a1-3188b2f4878d",
          "card": "7a02b32e-920d-4448-96f0-4d0a0c02b975",
          "suffix": "001",
          "rarity": "super"
        }
      ],
      "externalIDs": {}
    }
  ],
  "externalIDs": {
    "yugipedia": {
      "name": "Duelist League Series 5 participation card",
      "id": 2009
    }
  }
}