{
  "$schema": "https://raw.githubusercontent.com/DjobaDELATV/seygo_data/main/schema/v1/set.json",
  "id": "23b63221-48ba-4ea9-8aa2-b85e70dfa626",
  "name": {
    "en": "Limited Edition 10: Chaos Black",
    "ja": "\uff2c\uff29\uff2d\uff29\uff34\uff25\uff24 \uff25\uff24\uff29\uff34\uff29\uff2f\uff2e \uff11\uff10 \uff0d\uff23\uff28\uff21\uff2f\uff33 \uff22\uff2c\uff21\uff23\uff2b\uff0d"
  },
  "locales": {
    "jp": {
      "language": "ja",
      "prefix": "LE10-JP",
      "date": "2007-08-21",
      "image": "https://ms.yugipedia.com//a/aa/LE10CB-BoosterJP.png",
      "cardImages": {
        "unlimited": {
          "88ccc319-dd83-4fa1-8a61-0459b2c9fc67": "https://ms.yugipedia.com//9/9c/WhiteNightDragon-LE10-JP-UR.png",
          "ec661196-d505-406e-bd41-067abbf868d8": "https://ms.yugipedia.com//0/0e/ArcanaForceEXTheLightRuler-LE10-JP-UR.png",
          "d6c46404-6336-4c4e-94c0-42b12f776754": "https://ms.yugipedia.com//5/5b/CardBlocker-LE10-JP-UR.png"
        }
      },
      "cardInfo": {
        "unlimited": {
          "ec661196-d505-406e-bd41-067abbf868d8": {
            "image": "https://ms.yugipedia.com//0/0e/ArcanaForceEXTheLightRuler-LE10-JP-UR.png"
          },
          "88ccc319-dd83-4fa1-8a61-0459b2c9fc67": {
            "image": "https://ms.yugipedia.com//9/9c/WhiteNightDragon-LE10-JP-UR.png"
          },
          "d6c46404-6336-4c4e-94c0-42b12f776754": {
            "image": "https://ms.yugipedia.com//5/5b/CardBlocker-LE10-JP-UR.png"
          }
        }
      },
      "formats": [
        "ocg"
      ],
      "editions": [
        "unlimited"
      ],
      "externalIDs": {
        "dbIDs": [
          121209005
        ]
      }
    }
  },
  "contents": [
    {
      "locales": [
        "jp"
      ],
      "formats": [
        "ocg"
      ],
      "editions": [
        "unlimited"
      ],
      "image": "https://ms.yugipedia.com//a/aa/LE10CB-BoosterJP.png",
      "cards": [
        {
          "id": "d406cfc6-cd1e-4b61-b80a-fba92b235829",
          "card": "3f714338-8154-4886-be7e-5b80a16febe3",
          "suffix": "001",
          "rarity": "ultra"
        },
        {
          "id": "88ccc319-dd83-4fa1-8a61-0459b2c9fc67",
          "card": "7a9855ba-c2d6-4e9a-99b6-d777bee86bdc",
          "suffix": "002",
          "rarity": "ultra"
        },
        {
          "id": "ec661196-d505-406e-bd41-067abbf868d8",
          "card": "76d49051-842a-4af3-9973-f830725370c3",
          "suffix": "003",
          "rarity": "ultra"
        },
        {
          "id": "d6c46404-6336-4c4e-94c0-42b12f776754",
          "card": "857854bc-9989-408d-bd47-d698dad5dca3",
          "suffix": "004",
          "rarity": "ultra"
        }
      ],
      "externalIDs": {}
    }
  ],
  "externalIDs": {
    "yugipedia": {
      "name": "Limited Edition 10: Chaos Black",
      "id": 368174
    }
  }
}