{
  "$schema": "https://raw.githubusercontent.com/DjobaDELATV/seygo_data/main/schema/v1/set.json",
  "id": "7a3164b7-8c39-454d-a50d-f61883655380",
  "name": {
    "en": "Legend of Blue Eyes White Dragon",
    "ja": "\u9752\u773c\u306e\u767d\u9f8d\u4f1d\u8aac"
  },
  "locales": {
    "jp": {
      "language": "ja",
      "date": "2000-05-18",
      "image": "https://ms.yugipedia.com//0/0b/LB-BoosterJP.jpg",
      "cardImages": {},
      "cardInfo": {},
      "formats": [
        "ocg"
      ],
      "editions": [
        "unlimited"
      ],
      "externalIDs": {
        "dbIDs": [
          3302000
        ]
      }
    }
  },
  "contents": [],
  "externalIDs": {
    "yugipedia": {
      "name": "Legend of Blue Eyes White Dragon (Japanese)",
      "id": 224773
    }
  }
}