{
  "$schema": "https://raw.githubusercontent.com/DjobaDELATV/seygo_data/main/schema/v1/set.json",
  "id": "8125ab6b-ea7b-496f-b7fb-04e07c67881e",
  "name": {
    "en": "Legendary Arc-V Decks"
  },
  "locales": {
    "it": {
      "language": "it",
      "cardImages": {},
      "cardInfo": {},
      "formats": [
        "tcg"
      ],
      "editions": [
        "1st"
      ],
      "externalIDs": {}
    },
    "de": {
      "language": "de",
      "cardImages": {},
      "cardInfo": {},
      "formats": [
        "tcg"
      ],
      "editions": [
        "1st"
      ],
      "externalIDs": {}
    },
    "fr": {
      "language": "fr",
      "cardImages": {},
      "cardInfo": {},
      "formats": [
        "tcg"
      ],
      "editions": [
        "1st"
      ],
      "externalIDs": {}
    },
    "en": {
      "language": "en",
      "image": "https://ms.yugipedia.com//6/6b/LAVD-DeckEN.png",
      "cardImages": {},
      "cardInfo": {},
      "formats": [
        "tcg"
      ],
      "editions": [
        "1st"
      ],
      "externalIDs": {}
    },
    "pt": {
      "language": "pt",
      "cardImages": {},
      "cardInfo": {},
      "formats": [
        "tcg"
      ],
      "editions": [
        "1st"
      ],
      "externalIDs": {}
    },
    "sp": {
      "language": "es",
      "cardImages": {},
      "cardInfo": {},
      "formats": [
        "tcg"
      ],
      "editions": [
        "1st"
      ],
      "externalIDs": {}
    }
  },
  "contents": [],
  "externalIDs": {
    "yugipedia": {
      "name": "Legendary Arc-V Decks",
      "id": 1188095
    }
  }
}