{
  "$schema": "https://raw.githubusercontent.com/DjobaDELATV/seygo_data/main/schema/v1/set.json",
  "id": "b8e6bf59-f1f0-4e56-bc8e-06024bfcb0c3",
  "name": {
    "en": "Hobby League 5 participation card F"
  },
  "locales": {
    "en": {
      "language": "en",
      "prefix": "HL05-EN",
      "image": "https://ms.yugipedia.com//b/b5/HL-PromoEN.jpg",
      "cardImages": {
        "unlimited": {}
      },
      "cardInfo": {
        "unlimited": {}
      },
      "formats": [
        "tcg"
      ],
      "editions": [
        "unlimited"
      ],
      "externalIDs": {
        "dbIDs": [
          1121206006
        ]
      }
    }
  },
  "contents": [
    {
      "locales": [
        "en"
      ],
      "formats": [
        "tcg"
      ],
      "distrobution": "preconstructed",
      "editions": [
        "unlimited"
      ],
      "image": "https://ms.yugipedia.com//b/b5/HL-PromoEN.jpg",
      "cards": [
        {
          "id": "07cc8881-71cf-41db-be10-419300b4e54b",
          "card": "22529b15-79b2-4f67-8266-c34b4725cf24",
          "suffix": "006",
          "rarity": "ultraparallel"
        }
      ],
      "externalIDs": {}
    }
  ],
  "externalIDs": {
    "yugipedia": {
      "name": "Hobby League 5 participation card F",
      "id": 305560
    }
  }
}