{
  "$schema": "https://raw.githubusercontent.com/DjobaDELATV/seygo_data/main/schema/v1/set.json",
  "id": "e2727ef7-dc7f-49f9-a915-37e40d23837c",
  "name": {
    "en": "Yu-Gi-Oh! Worldwide Edition - Stairway to the Destined Duel - Bundles"
  },
  "locales": {
    "eu": {
      "language": "en",
      "prefix": "SDD-E",
      "date": "2003-04-17",
      "image": "https://ms.yugipedia.com//2/27/SDD-VideoGame-EU.jpg",
      "cardImages": {
        "unlimited": {
          "067138f3-33dc-476c-8ffd-24c76d44c0ba": "https://ms.yugipedia.com//f/fc/Seiyaryu-SDD-EU-PScR-UE.png",
          "de22cb25-0e75-4b31-9df8-76fb55d02f31": "https://ms.yugipedia.com//a/a8/AcidTrapHole-SDD-EU-PScR-UE.png",
          "4fddb779-7609-44eb-adf7-49484412c2be": "https://ms.yugipedia.com//2/22/Salamandra-SDD-EU-PScR-UE.png"
        }
      },
      "cardInfo": {
        "unlimited": {
          "de22cb25-0e75-4b31-9df8-76fb55d02f31": {
            "image": "https://ms.yugipedia.com//a/a8/AcidTrapHole-SDD-EU-PScR-UE.png"
          },
          "067138f3-33dc-476c-8ffd-24c76d44c0ba": {
            "image": "https://ms.yugipedia.com//f/fc/Seiyaryu-SDD-EU-PScR-UE.png"
          },
          "4fddb779-7609-44eb-adf7-49484412c2be": {
            "image": "https://ms.yugipedia.com//2/22/Salamandra-SDD-EU-PScR-UE.png"
          }
        }
      },
      "formats": [
        "tcg"
      ],
      "editions": [
        "unlimited"
      ],
      "externalIDs": {
        "dbIDs": [
          1141402001
        ]
      }
    },
    "na": {
      "language": "en",
      "prefix": "SDD-",
      "date": "2003-04-15",
      "image": "https://ms.yugipedia.com//b/bd/SDD-VideoGame-NA.jpg",
      "cardImages": {
        "unlimited": {
          "a73b5d13-3492-4fe1-8b05-7a13d975d663": "https://ms.yugipedia.com//3/3b/ValkyriontheMagnaWarrior-SDD-NA-PScR-UE.jpg",
          "c60281c6-ec12-4844-9ad7-19bc0c33b860": "https://ms.yugipedia.com//f/fc/SinisterSerpent-SDD-NA-PScR-UE.jpg",
          "a4c87ba3-529f-4cf0-b3cf-752b810bac4b": "https://ms.yugipedia.com//d/d7/HarpiesFeatherDuster-SDD-NA-PScR-UE.png"
        }
      },
      "cardInfo": {
        "unlimited": {
          "c60281c6-ec12-4844-9ad7-19bc0c33b860": {
            "image": "https://ms.yugipedia.com//f/fc/SinisterSerpent-SDD-NA-PScR-UE.jpg"
          },
          "a4c87ba3-529f-4cf0-b3cf-752b810bac4b": {
            "image": "https://ms.yugipedia.com//d/d7/HarpiesFeatherDuster-SDD-NA-PScR-UE.png"
          },
          "a73b5d13-3492-4fe1-8b05-7a13d975d663": {
            "image": "https://ms.yugipedia.com//3/3b/ValkyriontheMagnaWarrior-SDD-NA-PScR-UE.jpg"
          }
        }
      },
      "formats": [
        "tcg"
      ],
      "editions": [
        "unlimited"
      ],
      "externalIDs": {
        "dbIDs": [
          1141402001
        ]
      }
    }
  },
  "contents": [
    {
      "locales": [
        "eu"
      ],
      "formats": [
        "tcg"
      ],
      "distrobution": "preconstructed",
      "editions": [
        "unlimited"
      ],
      "image": "https://ms.yugipedia.com//2/27/SDD-VideoGame-EU.jpg",
      "cards": [
        {
          "id": "067138f3-33dc-476c-8ffd-24c76d44c0ba",
          "card": "95fee851-87f6-48f0-b4d1-7d97af26dbdb",
          "suffix": "001",
          "rarity": "prismaticsecret"
        },
        {
          "id": "de22cb25-0e75-4b31-9df8-76fb55d02f31",
          "card": "896ad640-40d3-4672-a87c-9f5e454bdef4",
          "suffix": "002",
          "rarity": "prismaticsecret"
        },
        {
          "id": "4fddb779-7609-44eb-adf7-49484412c2be",
          "card": "d797e807-bdf0-4bfc-901d-4e22e3350544",
          "suffix": "003",
          "rarity": "prismaticsecret"
        }
      ],
      "externalIDs": {}
    },
    {
      "locales": [
        "na"
      ],
      "formats": [
        "tcg"
      ],
      "distrobution": "preconstructed",
      "editions": [
        "unlimited"
      ],
      "image": "https://ms.yugipedia.com//b/bd/SDD-VideoGame-NA.jpg",
      "cards": [
        {
          "id": "a73b5d13-3492-4fe1-8b05-7a13d975d663",
          "card": "04f01e78-e2ea-494a-bff2-4e81e9362bbb",
          "suffix": "001",
          "rarity": "prismaticsecret"
        },
        {
          "id": "c60281c6-ec12-4844-9ad7-19bc0c33b860",
          "card": "97f5ff36-f57c-45b0-a62c-60d7ff1dcd8b",
          "suffix": "002",
          "rarity": "prismaticsecret"
        },
        {
          "id": "a4c87ba3-529f-4cf0-b3cf-752b810bac4b",
          "card": "46c86a80-238b-4ac7-ab62-79cd0b31094d",
          "suffix": "003",
          "rarity": "prismaticsecret"
        }
      ],
      "externalIDs": {}
    }
  ],
  "externalIDs": {
    "yugipedia": {
      "name": "Yu-Gi-Oh! Worldwide Edition: Stairway to the Destined Duel promotional cards",
      "id": 2019
    }
  }
}